forgeNN/__init__.py
forgeNN/layers.py
forgeNN/optimizers.py
forgeNN/tensor.py
forgeNN/training.py
forgeNN/vectorized.py
forgeNN/backends/__init__.py
forgeNN/backends/cpu.py
forgeNN/backends/cuda.py
forgeNN/core/tensor.py
forgeNN/model/io.py
forgeNN/nn/__init__.py
forgeNN/nn/activations.py
forgeNN/nn/losses.py
forgeNN/nn/metrics.py
forgeNN/nn/random.py
forgeNN/onnx/__init__.py
forgeNN/onnx/io.py
forgeNN/runtime/__init__.py
forgeNN/runtime/device.py
forgeNN/transformer/layers.py
forgenn-2.0.0.dist-info/licenses/LICENSE
forgenn-2.0.0.dist-info/METADATA
forgenn-2.0.0.dist-info/WHEEL
forgenn-2.0.0.dist-info/top_level.txt
forgenn-2.0.0.dist-info/RECORD
