Metadata-Version: 2.4
Name: forgeNN
Version: 2.0.0
Summary: A From Scratch Neural Network Framework with Educational Purposes
Author: Enbiya Çabuk
Author-email: cabuk23@itu.edu.tr
License: MIT License
Project-URL: Homepage, https://github.com/Savernish/forgeNN
Project-URL: Documentation, https://github.com/Savernish/forgeNN/blob/v2.0.0/README.md
Project-URL: Repository, https://github.com/Savernish/forgeNN/tree/v2.0.0
Project-URL: Bug Reports, https://github.com/Savernish/forgeNN/issues
Project-URL: Changelog, https://github.com/Savernish/forgeNN/blob/v2.0.0/CHANGELOG.md
Keywords: neural-networks,machine-learning,deep-learning,education,automatic-differentiation,numpy,from-scratch,ai,artificial-intelligence,pytorch,numba
Classifier: Development Status :: 4 - Beta
Classifier: Intended Audience :: Education
Classifier: Intended Audience :: Science/Research
Classifier: Intended Audience :: Developers
Classifier: Topic :: Scientific/Engineering :: Artificial Intelligence
Classifier: Topic :: Education
Classifier: Topic :: Software Development :: Libraries :: Python Modules
Classifier: License :: OSI Approved :: MIT License
Classifier: Programming Language :: Python :: 3
Classifier: Programming Language :: Python :: 3.8
Classifier: Programming Language :: Python :: 3.9
Classifier: Programming Language :: Python :: 3.10
Classifier: Programming Language :: Python :: 3.11
Classifier: Programming Language :: Python :: 3.12
Classifier: Operating System :: OS Independent
Requires-Python: >=3.8
License-File: LICENSE
Requires-Dist: numpy>=1.20.0
Requires-Dist: scikit-learn>=1.0.0
Requires-Dist: numba>=1.0.0
Provides-Extra: dev
Requires-Dist: pytest>=7.0.0; extra == "dev"
Requires-Dist: pytest-cov>=4.0.0; extra == "dev"
Requires-Dist: sphinx>=4.0.0; extra == "dev"
Requires-Dist: sphinx-rtd-theme>=1.0.0; extra == "dev"
Requires-Dist: black>=22.0.0; extra == "dev"
Requires-Dist: flake8>=4.0.0; extra == "dev"
Requires-Dist: mypy>=0.950; extra == "dev"
Requires-Dist: twine>=4.0.0; extra == "dev"
Requires-Dist: build>=0.8.0; extra == "dev"
Provides-Extra: examples
Requires-Dist: matplotlib>=3.5.0; extra == "examples"
Requires-Dist: jupyter>=1.0.0; extra == "examples"
Provides-Extra: onnx
Requires-Dist: onnx>=1.14.0; extra == "onnx"
Provides-Extra: cuda
Requires-Dist: cupy-cuda12x>=13.0.0; (platform_system == "Windows" or platform_system == "Linux") and extra == "cuda"
Provides-Extra: all
Requires-Dist: pytest>=7.0.0; extra == "all"
Requires-Dist: pytest-cov>=4.0.0; extra == "all"
Requires-Dist: sphinx>=4.0.0; extra == "all"
Requires-Dist: sphinx-rtd-theme>=1.0.0; extra == "all"
Requires-Dist: black>=22.0.0; extra == "all"
Requires-Dist: flake8>=4.0.0; extra == "all"
Requires-Dist: mypy>=0.950; extra == "all"
Requires-Dist: twine>=4.0.0; extra == "all"
Requires-Dist: build>=0.8.0; extra == "all"
Requires-Dist: matplotlib>=3.5.0; extra == "all"
Requires-Dist: jupyter>=1.0.0; extra == "all"
Requires-Dist: onnx>=1.14.0; extra == "all"
Requires-Dist: cupy-cuda12x>=13.0.0; (platform_system == "Windows" or platform_system == "Linux") and extra == "all"
Dynamic: license-file
